<?xml version="1.0" encoding="utf-8" ?>
<hibernate-mapping xmlns="urn:nhibernate-mapping-2.2">
  <class name="Cashier.Entity.WorkCalendarItem, Cashier.Entity" table="WorkCalendarItem" lazy="false">
    <id name="Id" column="Id" unsaved-value="0">
      <generator class="sequence">
        <param name="sequence">SQ_GLOBAL</param>
      </generator>
    </id>
    
    <property name="TypeItem" type="Int32"    not-null="true"/>
    <property name="Date"     type="DateTime" not-null="true"/>
   
  </class>
</hibernate-mapping>